Sqlalchemy11Documentation/README.md
Sqlalchemy11Documentation/__init__.py
Sqlalchemy11Documentation/__main__.py
Sqlalchemy11Documentation/file.epub
Sqlalchemy11Documentation/index.html
Sqlalchemy11Documentation/css/__init__.py
Sqlalchemy11Documentation/css/annotations.css
Sqlalchemy11Documentation/css/main.css
Sqlalchemy11Documentation/css/normalize.css
Sqlalchemy11Documentation/css/popup.css
Sqlalchemy11Documentation/font/__init__.py
Sqlalchemy11Documentation/font/fontello.eot
Sqlalchemy11Documentation/font/fontello.svg
Sqlalchemy11Documentation/font/fontello.ttf
Sqlalchemy11Documentation/font/fontello.woff
Sqlalchemy11Documentation/img/__init__.py
Sqlalchemy11Documentation/img/annotator-glyph-sprite.png
Sqlalchemy11Documentation/img/annotator-icon-sprite.png
Sqlalchemy11Documentation/img/apple-touch-icon.png
Sqlalchemy11Documentation/img/cancelfullscreen.png
Sqlalchemy11Documentation/img/close.png
Sqlalchemy11Documentation/img/fullscreen.png
Sqlalchemy11Documentation/img/loader.gif
Sqlalchemy11Documentation/img/menu-icon.png
Sqlalchemy11Documentation/img/save.png
Sqlalchemy11Documentation/img/saved.png
Sqlalchemy11Documentation/img/settings-s.png
Sqlalchemy11Documentation/img/settings.png
Sqlalchemy11Documentation/img/star.png
Sqlalchemy11Documentation/js/__init__.py
Sqlalchemy11Documentation/js/epub.js
Sqlalchemy11Documentation/js/epub.min.js
Sqlalchemy11Documentation/js/epub.min.map
Sqlalchemy11Documentation/js/hooks.min.js
Sqlalchemy11Documentation/js/hooks.min.map
Sqlalchemy11Documentation/js/reader.js
Sqlalchemy11Documentation/js/reader.js.map
Sqlalchemy11Documentation/js/reader.min.js
Sqlalchemy11Documentation/js/reader.min.map
Sqlalchemy11Documentation/js/hooks/__init__.py
Sqlalchemy11Documentation/js/hooks/extensions/__init__.py
Sqlalchemy11Documentation/js/hooks/extensions/highlight.js
Sqlalchemy11Documentation/js/libs/__init__.py
Sqlalchemy11Documentation/js/libs/jquery.min.js
Sqlalchemy11Documentation/js/libs/localforage.min.js
sqlalchemy_1_1_documentation-2024.3.2.0.dist-info/METADATA
sqlalchemy_1_1_documentation-2024.3.2.0.dist-info/WHEEL
sqlalchemy_1_1_documentation-2024.3.2.0.dist-info/entry_points.txt
sqlalchemy_1_1_documentation-2024.3.2.0.dist-info/top_level.txt
sqlalchemy_1_1_documentation-2024.3.2.0.dist-info/RECORD
